[
    {
        "match": "Switzerland vs Colombia",
        "sources": [
            {
                "cover": null,
                "createTime": "0",
                "duration": "0",
                "id": "0",
                "path": "https://play.88player.top/m3u8.html?url=https://www.rtmpcdn.com/live/migu1.m3u8",
                "stat": null,
                "title": "Channel 1"
            },
            {
                "cover": null,
                "createTime": "0",
                "duration": "0",
                "id": "0",
                "path": "https://play.88player.top/m3u8.html?url=https://www.rtmpcdn.com/live/cctv5.m3u8",
                "stat": null,
                "title": "Channel 2"
            },
            {
                "cover": null,
                "createTime": "0",
                "duration": "0",
                "id": "0",
                "path": "https://play.88player.top/m3u8.html?url=https://www.rtmpcdn.com/live/xiaohongshu1.m3u8",
                "stat": null,
                "title": "Channel 3"
            }
        ]
    }
]